{
  "annotations": {
    "list": [
      {
        "builtIn": 1,
        "datasource": {
          "type": "grafana",
          "uid": "-- Grafana --"
        },
        "enable": true,
        "hide": true,
        "iconColor": "rgba(0, 211, 255, 1)",
        "name": "Annotations & Alerts",
        "type": "dashboard"
      }
    ]
  },
  "editable": true,
  "fiscalYearStartMonth": 0,
  "graphTooltip": 0,
  "id": 3,
  "links": [],
  "panels": [
    {
      "datasource": {
        "type": "grafana-postgresql-datasource",
        "uid": "P44368ADAD746BC27"
      },
      "fieldConfig": {
        "defaults": {
          "color": {
            "mode": "thresholds"
          },
          "mappings": [],
          "thresholds": {
            "mode": "absolute",
            "steps": [
              {
                "color": "green",
                "value": null
              },
              {
                "color": "red",
                "value": 80
              }
            ]
          }
        },
        "overrides": []
      },
      "gridPos": {
        "h": 4,
        "w": 6,
        "x": 0,
        "y": 0
      },
      "id": 4,
      "options": {
        "infinitePan": false,
        "inlineEditing": true,
        "panZoom": false,
        "root": {
          "background": {
            "color": {
              "fixed": "transparent"
            },
            "image": {
              "fixed": "img/bg/logo-set.png",
              "mode": "fixed"
            },
            "size": "fill"
          },
          "border": {
            "color": {
              "fixed": "dark-green"
            }
          },
          "constraint": {
            "horizontal": "left",
            "vertical": "top"
          },
          "elements": [],
          "name": "Element 1732872062800",
          "oneClickMode": "off",
          "placement": {
            "height": 100,
            "left": 0,
            "rotation": 0,
            "top": 0,
            "width": 100
          },
          "type": "frame"
        },
        "showAdvancedTypes": true
      },
      "pluginVersion": "11.3.0",
      "targets": [
        {
          "refId": "A"
        }
      ],
      "title": "",
      "type": "canvas"
    },
    {
      "datasource": {
        "type": "grafana-postgresql-datasource",
        "uid": "P44368ADAD746BC27"
      },
      "fieldConfig": {
        "defaults": {
          "color": {
            "mode": "thresholds"
          },
          "mappings": [],
          "thresholds": {
            "mode": "absolute",
            "steps": [
              {
                "color": "green",
                "value": null
              },
              {
                "color": "red",
                "value": 80
              }
            ]
          }
        },
        "overrides": []
      },
      "gridPos": {
        "h": 7,
        "w": 6,
        "x": 6,
        "y": 0
      },
      "id": 3,
      "options": {
        "infinitePan": false,
        "inlineEditing": true,
        "panZoom": false,
        "root": {
          "background": {
            "color": {
              "fixed": "transparent"
            },
            "image": {
              "fixed": "img/bg/logo-soul-k.png",
              "mode": "fixed"
            },
            "size": "fill"
          },
          "border": {
            "color": {
              "fixed": "dark-green"
            }
          },
          "constraint": {
            "horizontal": "left",
            "vertical": "top"
          },
          "elements": [],
          "name": "Element 1732871568155",
          "oneClickMode": "off",
          "placement": {
            "height": 100,
            "left": 0,
            "rotation": 0,
            "top": 0,
            "width": 100
          },
          "type": "frame"
        },
        "showAdvancedTypes": true
      },
      "pluginVersion": "11.3.0",
      "targets": [
        {
          "refId": "A"
        }
      ],
      "title": "",
      "type": "canvas"
    },
    {
      "datasource": {
        "type": "grafana-postgresql-datasource",
        "uid": "P44368ADAD746BC27"
      },
      "fieldConfig": {
        "defaults": {
          "color": {
            "mode": "thresholds"
          },
          "mappings": [],
          "thresholds": {
            "mode": "absolute",
            "steps": [
              {
                "color": "green",
                "value": null
              },
              {
                "color": "red",
                "value": 80
              }
            ]
          }
        },
        "overrides": []
      },
      "gridPos": {
        "h": 7,
        "w": 6,
        "x": 12,
        "y": 0
      },
      "id": 13,
      "options": {
        "infinitePan": false,
        "inlineEditing": true,
        "panZoom": false,
        "root": {
          "background": {
            "color": {
              "fixed": "transparent"
            },
            "image": {
              "fixed": "img/bg/titolo.png",
              "mode": "fixed"
            },
            "size": "fill"
          },
          "border": {
            "color": {
              "fixed": "dark-green"
            }
          },
          "constraint": {
            "horizontal": "left",
            "vertical": "top"
          },
          "elements": [],
          "name": "Element 1732893348657",
          "oneClickMode": "off",
          "placement": {
            "height": 100,
            "left": 0,
            "rotation": 0,
            "top": 0,
            "width": 100
          },
          "type": "frame"
        },
        "showAdvancedTypes": true
      },
      "pluginVersion": "11.3.0",
      "targets": [
        {
          "refId": "A"
        }
      ],
      "title": "",
      "type": "canvas"
    },
    {
      "datasource": {
        "type": "grafana-postgresql-datasource",
        "uid": "P44368ADAD746BC27"
      },
      "fieldConfig": {
        "defaults": {
          "color": {
            "mode": "thresholds"
          },
          "mappings": [],
          "thresholds": {
            "mode": "absolute",
            "steps": [
              {
                "color": "green",
                "value": null
              },
              {
                "color": "red",
                "value": 80
              }
            ]
          }
        },
        "overrides": []
      },
      "gridPos": {
        "h": 3,
        "w": 6,
        "x": 0,
        "y": 4
      },
      "id": 2,
      "options": {
        "infinitePan": false,
        "inlineEditing": true,
        "panZoom": false,
        "root": {
          "background": {
            "color": {
              "fixed": "transparent"
            },
            "image": {
              "fixed": "img/bg/logo-SIEMENS.png",
              "mode": "fixed"
            },
            "size": "fill"
          },
          "border": {
            "color": {
              "fixed": "dark-green"
            }
          },
          "constraint": {
            "horizontal": "left",
            "vertical": "top"
          },
          "elements": [],
          "name": "Element 1732871374382",
          "oneClickMode": "off",
          "placement": {
            "height": 100,
            "left": 0,
            "rotation": 0,
            "top": 0,
            "width": 100
          },
          "type": "frame"
        },
        "showAdvancedTypes": true
      },
      "pluginVersion": "11.3.0",
      "targets": [
        {
          "refId": "A"
        }
      ],
      "title": "",
      "type": "canvas"
    },
    {
      "datasource": {
        "type": "grafana-postgresql-datasource",
        "uid": "P44368ADAD746BC27"
      },
      "fieldConfig": {
        "defaults": {
          "color": {
            "mode": "palette-classic"
          },
          "custom": {
            "axisBorderShow": false,
            "axisCenteredZero": false,
            "axisColorMode": "text",
            "axisLabel": "",
            "axisPlacement": "left",
            "axisSoftMax": 100,
            "axisSoftMin": 0,
            "barAlignment": 0,
            "barWidthFactor": 0.6,
            "drawStyle": "line",
            "fillOpacity": 0,
            "gradientMode": "none",
            "hideFrom": {
              "legend": false,
              "tooltip": false,
              "viz": false
            },
            "insertNulls": false,
            "lineInterpolation": "linear",
            "lineStyle": {
              "fill": "solid"
            },
            "lineWidth": 1,
            "pointSize": 5,
            "scaleDistribution": {
              "type": "linear"
            },
            "showPoints": "auto",
            "spanNulls": false,
            "stacking": {
              "group": "A",
              "mode": "none"
            },
            "thresholdsStyle": {
              "mode": "dashed+area"
            }
          },
          "mappings": [],
          "max": 400,
          "min": 0,
          "thresholds": {
            "mode": "absolute",
            "steps": [
              {
                "color": "green",
                "value": null
              },
              {
                "color": "#EAB839",
                "value": 75
              },
              {
                "color": "red",
                "value": 90
              }
            ]
          },
          "unit": "celsius"
        },
        "overrides": []
      },
      "gridPos": {
        "h": 8,
        "w": 12,
        "x": 0,
        "y": 7
      },
      "id": 5,
      "options": {
        "legend": {
          "calcs": [],
          "displayMode": "table",
          "placement": "bottom",
          "showLegend": false
        },
        "tooltip": {
          "mode": "single",
          "sort": "none"
        }
      },
      "pluginVersion": "11.3.0",
      "targets": [
        {
          "editorMode": "code",
          "format": "table",
          "rawQuery": true,
          "rawSql": "SELECT temperature, ora FROM brasiera_con_mixer_vapore where id = 1 ORDER BY ora DESC",
          "refId": "A",
          "sql": {
            "columns": [
              {
                "parameters": [
                  {
                    "name": "temperature",
                    "type": "functionParameter"
                  }
                ],
                "type": "function"
              },
              {
                "parameters": [
                  {
                    "name": "ora",
                    "type": "functionParameter"
                  }
                ],
                "type": "function"
              }
            ],
            "groupBy": [
              {
                "property": {
                  "type": "string"
                },
                "type": "groupBy"
              }
            ],
            "limit": 50
          },
          "table": "brasiera_con_mixer_vapore"
        }
      ],
      "title": "Temperature",
      "type": "timeseries"
    },
    {
      "datasource": {
        "type": "grafana-postgresql-datasource",
        "uid": "P44368ADAD746BC27"
      },
      "fieldConfig": {
        "defaults": {
          "color": {
            "mode": "thresholds"
          },
          "fieldMinMax": false,
          "mappings": [],
          "thresholds": {
            "mode": "absolute",
            "steps": [
              {
                "color": "green",
                "value": null
              },
              {
                "color": "#EAB839",
                "value": 75
              },
              {
                "color": "red",
                "value": 90
              }
            ]
          }
        },
        "overrides": [
          {
            "matcher": {
              "id": "byName",
              "options": "temperature"
            },
            "properties": [
              {
                "id": "unit",
                "value": "celsius"
              },
              {
                "id": "min",
                "value": 0
              },
              {
                "id": "max",
                "value": 100
              },
              {
                "id": "decimals",
                "value": 1
              }
            ]
          },
          {
            "matcher": {
              "id": "byName",
              "options": "pressure"
            },
            "properties": [
              {
                "id": "unit",
                "value": "pressurebar"
              },
              {
                "id": "min",
                "value": 0
              },
              {
                "id": "max",
                "value": 100
              },
              {
                "id": "decimals",
                "value": 1
              }
            ]
          }
        ]
      },
      "gridPos": {
        "h": 16,
        "w": 6,
        "x": 12,
        "y": 7
      },
      "id": 1,
      "options": {
        "minVizHeight": 75,
        "minVizWidth": 75,
        "orientation": "horizontal",
        "reduceOptions": {
          "calcs": [
            "lastNotNull"
          ],
          "fields": "",
          "values": false
        },
        "showThresholdLabels": false,
        "showThresholdMarkers": true,
        "sizing": "auto",
        "text": {}
      },
      "pluginVersion": "11.3.0",
      "targets": [
        {
          "datasource": {
            "type": "grafana-postgresql-datasource",
            "uid": "P44368ADAD746BC27"
          },
          "editorMode": "code",
          "format": "table",
          "rawQuery": true,
          "rawSql": "SELECT temperature, pressure FROM brasiera_con_mixer_vapore Where ID = 1 ORDER BY ora desc limit 1",
          "refId": "A",
          "sql": {
            "columns": [
              {
                "parameters": [
                  {
                    "name": "temperature",
                    "type": "functionParameter"
                  }
                ],
                "type": "function"
              },
              {
                "parameters": [
                  {
                    "name": "pression",
                    "type": "functionParameter"
                  }
                ],
                "type": "function"
              }
            ],
            "groupBy": [
              {
                "property": {
                  "type": "string"
                },
                "type": "groupBy"
              }
            ],
            "limit": 50
          },
          "table": "brasiera_con_mixer_vapore"
        }
      ],
      "title": "",
      "type": "gauge"
    },
    {
      "datasource": {
        "type": "grafana-postgresql-datasource",
        "uid": "P44368ADAD746BC27"
      },
      "fieldConfig": {
        "defaults": {
          "color": {
            "mode": "palette-classic"
          },
          "custom": {
            "axisBorderShow": false,
            "axisCenteredZero": false,
            "axisColorMode": "text",
            "axisLabel": "",
            "axisPlacement": "left",
            "axisSoftMax": 100,
            "axisSoftMin": 0,
            "barAlignment": 0,
            "barWidthFactor": 0.6,
            "drawStyle": "line",
            "fillOpacity": 0,
            "gradientMode": "none",
            "hideFrom": {
              "legend": false,
              "tooltip": false,
              "viz": false
            },
            "insertNulls": false,
            "lineInterpolation": "linear",
            "lineStyle": {
              "fill": "solid"
            },
            "lineWidth": 1,
            "pointSize": 5,
            "scaleDistribution": {
              "type": "linear"
            },
            "showPoints": "always",
            "spanNulls": false,
            "stacking": {
              "group": "A",
              "mode": "none"
            },
            "thresholdsStyle": {
              "mode": "dashed+area"
            }
          },
          "mappings": [],
          "max": 100,
          "min": 0,
          "thresholds": {
            "mode": "absolute",
            "steps": [
              {
                "color": "green",
                "value": null
              },
              {
                "color": "#EAB839",
                "value": 75
              },
              {
                "color": "red",
                "value": 90
              }
            ]
          },
          "unit": "pressurebar"
        },
        "overrides": []
      },
      "gridPos": {
        "h": 8,
        "w": 12,
        "x": 0,
        "y": 15
      },
      "id": 6,
      "options": {
        "legend": {
          "calcs": [],
          "displayMode": "list",
          "placement": "bottom",
          "showLegend": false
        },
        "tooltip": {
          "mode": "single",
          "sort": "none"
        }
      },
      "pluginVersion": "11.3.0",
      "targets": [
        {
          "editorMode": "code",
          "format": "table",
          "rawQuery": true,
          "rawSql": "SELECT pressure, ora FROM brasiera_con_mixer_vapore where id = 1 ORDER BY ora DESC",
          "refId": "A",
          "sql": {
            "columns": [
              {
                "parameters": [],
                "type": "function"
              },
              {
                "parameters": [],
                "type": "function"
              }
            ],
            "groupBy": [
              {
                "property": {
                  "type": "string"
                },
                "type": "groupBy"
              }
            ],
            "limit": 50
          }
        }
      ],
      "title": "Pressure",
      "type": "timeseries"
    },
    {
      "datasource": {
        "type": "grafana-postgresql-datasource",
        "uid": "P44368ADAD746BC27"
      },
      "fieldConfig": {
        "defaults": {
          "color": {
            "fixedColor": "yellow",
            "mode": "fixed"
          },
          "custom": {
            "axisBorderShow": false,
            "axisCenteredZero": false,
            "axisColorMode": "text",
            "axisLabel": "",
            "axisPlacement": "auto",
            "barAlignment": 0,
            "barWidthFactor": 0.6,
            "drawStyle": "line",
            "fillOpacity": 23,
            "gradientMode": "none",
            "hideFrom": {
              "legend": false,
              "tooltip": false,
              "viz": false
            },
            "insertNulls": false,
            "lineInterpolation": "linear",
            "lineWidth": 1,
            "pointSize": 5,
            "scaleDistribution": {
              "type": "linear"
            },
            "showPoints": "auto",
            "spanNulls": false,
            "stacking": {
              "group": "A",
              "mode": "none"
            },
            "thresholdsStyle": {
              "mode": "off"
            }
          },
          "mappings": [],
          "thresholds": {
            "mode": "absolute",
            "steps": [
              {
                "color": "green",
                "value": null
              },
              {
                "color": "red",
                "value": 80
              }
            ]
          }
        },
        "overrides": []
      },
      "gridPos": {
        "h": 7,
        "w": 12,
        "x": 0,
        "y": 23
      },
      "id": 12,
      "options": {
        "legend": {
          "calcs": [],
          "displayMode": "list",
          "placement": "bottom",
          "showLegend": true
        },
        "tooltip": {
          "mode": "single",
          "sort": "none"
        }
      },
      "pluginVersion": "11.3.0",
      "targets": [
        {
          "editorMode": "builder",
          "format": "table",
          "rawQuery": true,
          "rawSql": "SELECT ora, SUM(consumi) FROM brasiera_con_mixer_vapore GROUP BY ora LIMIT 50 ",
          "refId": "A",
          "sql": {
            "columns": [
              {
                "parameters": [
                  {
                    "name": "ora",
                    "type": "functionParameter"
                  }
                ],
                "type": "function"
              },
              {
                "name": "SUM",
                "parameters": [
                  {
                    "name": "consumi",
                    "type": "functionParameter"
                  }
                ],
                "type": "function"
              }
            ],
            "groupBy": [
              {
                "property": {
                  "name": "ora",
                  "type": "string"
                },
                "type": "groupBy"
              }
            ],
            "limit": 50
          },
          "table": "brasiera_con_mixer_vapore"
        }
      ],
      "title": "Consumi",
      "type": "timeseries"
    },
    {
      "datasource": {
        "type": "grafana-postgresql-datasource",
        "uid": "P44368ADAD746BC27"
      },
      "fieldConfig": {
        "defaults": {
          "color": {
            "mode": "thresholds"
          },
          "mappings": [],
          "thresholds": {
            "mode": "absolute",
            "steps": [
              {
                "color": "green",
                "value": null
              },
              {
                "color": "red",
                "value": 5000
              }
            ]
          },
          "unit": "kwatth"
        },
        "overrides": []
      },
      "gridPos": {
        "h": 7,
        "w": 6,
        "x": 12,
        "y": 23
      },
      "id": 15,
      "options": {
        "infinitePan": false,
        "inlineEditing": true,
        "panZoom": false,
        "root": {
          "background": {
            "color": {
              "fixed": "transparent"
            },
            "size": "fill"
          },
          "border": {
            "color": {
              "fixed": "dark-green"
            }
          },
          "constraint": {
            "horizontal": "left",
            "vertical": "top"
          },
          "elements": [
            {
              "background": {
                "color": {
                  "field": "sum",
                  "fixed": "#D9D9D9"
                }
              },
              "border": {
                "color": {
                  "fixed": "dark-green"
                }
              },
              "config": {
                "align": "center",
                "color": {
                  "fixed": "#000000"
                },
                "size": 40,
                "text": {
                  "field": "sum",
                  "fixed": "",
                  "mode": "field"
                },
                "valign": "middle"
              },
              "connections": [],
              "constraint": {
                "horizontal": "left",
                "vertical": "top"
              },
              "links": [],
              "name": "Element 1",
              "oneClickMode": "off",
              "placement": {
                "height": 200,
                "left": 10,
                "top": 9,
                "width": 455
              },
              "type": "metric-value"
            }
          ],
          "name": "Element 1732893672654",
          "oneClickMode": "off",
          "placement": {
            "height": 100,
            "left": 0,
            "rotation": 0,
            "top": 0,
            "width": 100
          },
          "type": "frame"
        },
        "showAdvancedTypes": true
      },
      "pluginVersion": "11.3.0",
      "targets": [
        {
          "editorMode": "code",
          "format": "table",
          "rawQuery": true,
          "rawSql": "SELECT SUM(consumi) FROM brasiera_con_mixer_vapore where id=1",
          "refId": "A",
          "sql": {
            "columns": [
              {
                "name": "SUM",
                "parameters": [
                  {
                    "name": "consumi",
                    "type": "functionParameter"
                  }
                ],
                "type": "function"
              }
            ],
            "groupBy": [
              {
                "property": {
                  "type": "string"
                },
                "type": "groupBy"
              }
            ],
            "limit": 50
          },
          "table": "brasiera_con_mixer_vapore"
        }
      ],
      "title": "Consumi globali macchina",
      "type": "canvas"
    },
    {
      "datasource": {
        "type": "grafana-postgresql-datasource",
        "uid": "P44368ADAD746BC27"
      },
      "fieldConfig": {
        "defaults": {
          "color": {
            "mode": "palette-classic"
          },
          "custom": {
            "axisBorderShow": false,
            "axisCenteredZero": false,
            "axisColorMode": "text",
            "axisLabel": "",
            "axisPlacement": "auto",
            "barAlignment": -1,
            "barWidthFactor": 0.5,
            "drawStyle": "line",
            "fillOpacity": 30,
            "gradientMode": "none",
            "hideFrom": {
              "legend": false,
              "tooltip": false,
              "viz": false
            },
            "insertNulls": false,
            "lineInterpolation": "linear",
            "lineStyle": {
              "fill": "solid"
            },
            "lineWidth": 1,
            "pointSize": 5,
            "scaleDistribution": {
              "type": "linear"
            },
            "showPoints": "never",
            "spanNulls": false,
            "stacking": {
              "group": "A",
              "mode": "none"
            },
            "thresholdsStyle": {
              "mode": "off"
            }
          },
          "mappings": [],
          "thresholds": {
            "mode": "absolute",
            "steps": [
              {
                "color": "green",
                "value": null
              },
              {
                "color": "red",
                "value": 80
              }
            ]
          }
        },
        "overrides": []
      },
      "gridPos": {
        "h": 7,
        "w": 12,
        "x": 0,
        "y": 30
      },
      "id": 11,
      "options": {
        "legend": {
          "calcs": [],
          "displayMode": "list",
          "placement": "bottom",
          "showLegend": true
        },
        "tooltip": {
          "mode": "single",
          "sort": "none"
        }
      },
      "pluginVersion": "11.3.0",
      "targets": [
        {
          "editorMode": "code",
          "format": "table",
          "rawQuery": true,
          "rawSql": "SELECT ora, on_off FROM brasiera_con_mixer_vapore where id=1 order by ora desc",
          "refId": "A",
          "sql": {
            "columns": [
              {
                "parameters": [
                  {
                    "name": "ora",
                    "type": "functionParameter"
                  }
                ],
                "type": "function"
              },
              {
                "parameters": [
                  {
                    "name": "on_off",
                    "type": "functionParameter"
                  }
                ],
                "type": "function"
              }
            ],
            "groupBy": [
              {
                "property": {
                  "type": "string"
                },
                "type": "groupBy"
              }
            ],
            "limit": 50
          },
          "table": "brasiera_con_mixer_vapore"
        }
      ],
      "title": "ON / OFF",
      "type": "timeseries"
    },
    {
      "fieldConfig": {
        "defaults": {},
        "overrides": []
      },
      "gridPos": {
        "h": 6,
        "w": 20,
        "x": 0,
        "y": 37
      },
      "id": 8,
      "options": {
        "alertInstanceLabelFilter": "",
        "alertName": "",
        "dashboardAlerts": false,
        "folder": {
          "title": "Cucina",
          "uid": "de59hwmibmpz4c"
        },
        "groupBy": [],
        "groupMode": "default",
        "maxItems": 20,
        "sortOrder": 1,
        "stateFilter": {
          "error": true,
          "firing": true,
          "noData": false,
          "normal": false,
          "pending": true
        },
        "viewMode": "list"
      },
      "pluginVersion": "11.3.0",
      "title": "Panel Title",
      "type": "alertlist"
    }
  ],
  "preload": false,
  "refresh": "5s",
  "schemaVersion": 40,
  "tags": [],
  "templating": {
    "list": []
  },
  "time": {
    "from": "2024-11-29T15:27:24.062Z",
    "to": "2024-11-29T15:37:24.062Z"
  },
  "timepicker": {},
  "timezone": "browser",
  "title": "Brasiera 1",
  "uid": "ee59hvuq2aha8c",
  "version": 49,
  "weekStart": ""
}